{"response":{"verses":[{"auditid":"0","verse":"1","lastverse":"1","id":"fra-LSG:Ps.2.1","osis_end":"fra-LSG:Ps.2.1","label":"","reference":"Psaumes 2:1","prev_osis_id":"Ps.001.006,fra-LSG","next_osis_id":"Ps.002.002,fra-LSG","text":"<h5 class=\"r\">(Ac 4:25-28; 13:27-41. Mt 21:37-45. Ph 2:9-11.) Ps 18:51; 21:9, etc.; 110. Jn 3:36.<\/h5>\n<p class=\"q\"><sup id=\"Ps.2.1\" class=\"v\">1<\/sup>Pourquoi ce tumulte parmi les nations,<\/p>\n<p class=\"q\">Ces vaines pens\u00e9es parmi les peuples?<\/p>","parent":{"chapter":{"path":"\/chapters\/fra-LSG:Ps.2","name":"Psaumes 2","id":"fra-LSG:Ps.2"}},"next":{"verse":{"path":"\/verses\/fra-LSG:Ps.2.2","name":"Psaumes 2:2","id":"fra-LSG:Ps.2.2"}},"previous":{"verse":{"path":"\/verses\/fra-LSG:Ps.1.6","name":"Psaumes 1:6","id":"fra-LSG:Ps.1.6"}},"copyright":"Public Domain"},{"auditid":"0","verse":"2","lastverse":"2","id":"fra-LSG:Ps.2.2","osis_end":"fra-LSG:Ps.2.2","label":"","reference":"Psaumes 2:2","prev_osis_id":"Ps.002.001,fra-LSG","next_osis_id":"Ps.002.003,fra-LSG","text":"<p class=\"q\"><sup id=\"Ps.2.2\" class=\"v\">2<\/sup>Pourquoi les rois de la terre se soul\u00e8vent-ils<\/p>\n<p class=\"q\">Et les princes se liguent-ils avec eux<\/p>\n<p class=\"q\">Contre l\u2019\u00c9ternel et contre son oint?<\/p>","parent":{"chapter":{"path":"\/chapters\/fra-LSG:Ps.2","name":"Psaumes 2","id":"fra-LSG:Ps.2"}},"next":{"verse":{"path":"\/verses\/fra-LSG:Ps.2.3","name":"Psaumes 2:3","id":"fra-LSG:Ps.2.3"}},"previous":{"verse":{"path":"\/verses\/fra-LSG:Ps.2.1","name":"Psaumes 2:1","id":"fra-LSG:Ps.2.1"}},"copyright":"Public Domain"},{"auditid":"0","verse":"3","lastverse":"3","id":"fra-LSG:Ps.2.3","osis_end":"fra-LSG:Ps.2.3","label":"","reference":"Psaumes 2:3","prev_osis_id":"Ps.002.002,fra-LSG","next_osis_id":"Ps.002.004,fra-LSG","text":"<p class=\"q\"><sup id=\"Ps.2.3\" class=\"v\">3<\/sup>Brisons leurs liens,<\/p>\n<p class=\"q\">D\u00e9livrons-nous de leurs cha\u00eenes!<\/p>","parent":{"chapter":{"path":"\/chapters\/fra-LSG:Ps.2","name":"Psaumes 2","id":"fra-LSG:Ps.2"}},"next":{"verse":{"path":"\/verses\/fra-LSG:Ps.2.4","name":"Psaumes 2:4","id":"fra-LSG:Ps.2.4"}},"previous":{"verse":{"path":"\/verses\/fra-LSG:Ps.2.2","name":"Psaumes 2:2","id":"fra-LSG:Ps.2.2"}},"copyright":"Public Domain"},{"auditid":"0","verse":"4","lastverse":"4","id":"fra-LSG:Ps.2.4","osis_end":"fra-LSG:Ps.2.4","label":"","reference":"Psaumes 2:4","prev_osis_id":"Ps.002.003,fra-LSG","next_osis_id":"Ps.002.005,fra-LSG","text":"<p class=\"q\"><sup id=\"Ps.2.4\" class=\"v\">4<\/sup>Celui qui si\u00e8ge dans les cieux rit,<\/p>\n<p class=\"q\">Le Seigneur se moque d\u2019eux.<\/p>","parent":{"chapter":{"path":"\/chapters\/fra-LSG:Ps.2","name":"Psaumes 2","id":"fra-LSG:Ps.2"}},"next":{"verse":{"path":"\/verses\/fra-LSG:Ps.2.5","name":"Psaumes 2:5","id":"fra-LSG:Ps.2.5"}},"previous":{"verse":{"path":"\/verses\/fra-LSG:Ps.2.3","name":"Psaumes 2:3","id":"fra-LSG:Ps.2.3"}},"copyright":"Public Domain"},{"auditid":"0","verse":"5","lastverse":"5","id":"fra-LSG:Ps.2.5","osis_end":"fra-LSG:Ps.2.5","label":"","reference":"Psaumes 2:5","prev_osis_id":"Ps.002.004,fra-LSG","next_osis_id":"Ps.002.006,fra-LSG","text":"<p class=\"q\"><sup id=\"Ps.2.5\" class=\"v\">5<\/sup>Puis il leur parle dans sa col\u00e8re,<\/p>\n<p class=\"q\">Il les \u00e9pouvante dans sa fureur:<\/p>","parent":{"chapter":{"path":"\/chapters\/fra-LSG:Ps.2","name":"Psaumes 2","id":"fra-LSG:Ps.2"}},"next":{"verse":{"path":"\/verses\/fra-LSG:Ps.2.6","name":"Psaumes 2:6","id":"fra-LSG:Ps.2.6"}},"previous":{"verse":{"path":"\/verses\/fra-LSG:Ps.2.4","name":"Psaumes 2:4","id":"fra-LSG:Ps.2.4"}},"copyright":"Public Domain"},{"auditid":"0","verse":"6","lastverse":"6","id":"fra-LSG:Ps.2.6","osis_end":"fra-LSG:Ps.2.6","label":"","reference":"Psaumes 2:6","prev_osis_id":"Ps.002.005,fra-LSG","next_osis_id":"Ps.002.007,fra-LSG","text":"<p class=\"q\"><sup id=\"Ps.2.6\" class=\"v\">6<\/sup>C\u2019est moi qui ai oint mon roi<\/p>\n<p class=\"q\">Sur Sion, ma montagne sainte!<\/p>","parent":{"chapter":{"path":"\/chapters\/fra-LSG:Ps.2","name":"Psaumes 2","id":"fra-LSG:Ps.2"}},"next":{"verse":{"path":"\/verses\/fra-LSG:Ps.2.7","name":"Psaumes 2:7","id":"fra-LSG:Ps.2.7"}},"previous":{"verse":{"path":"\/verses\/fra-LSG:Ps.2.5","name":"Psaumes 2:5","id":"fra-LSG:Ps.2.5"}},"copyright":"Public Domain"},{"auditid":"0","verse":"7","lastverse":"7","id":"fra-LSG:Ps.2.7","osis_end":"fra-LSG:Ps.2.7","label":"","reference":"Psaumes 2:7","prev_osis_id":"Ps.002.006,fra-LSG","next_osis_id":"Ps.002.008,fra-LSG","text":"<p class=\"q\"><sup id=\"Ps.2.7\" class=\"v\">7<\/sup>Je publierai le d\u00e9cret;<\/p>\n<p class=\"q\">L\u2019\u00c9ternel m\u2019a dit: Tu es mon fils!<\/p>\n<p class=\"q\">Je t\u2019ai engendr\u00e9 aujourd\u2019hui.<\/p>","parent":{"chapter":{"path":"\/chapters\/fra-LSG:Ps.2","name":"Psaumes 2","id":"fra-LSG:Ps.2"}},"next":{"verse":{"path":"\/verses\/fra-LSG:Ps.2.8","name":"Psaumes 2:8","id":"fra-LSG:Ps.2.8"}},"previous":{"verse":{"path":"\/verses\/fra-LSG:Ps.2.6","name":"Psaumes 2:6","id":"fra-LSG:Ps.2.6"}},"copyright":"Public Domain"},{"auditid":"0","verse":"8","lastverse":"8","id":"fra-LSG:Ps.2.8","osis_end":"fra-LSG:Ps.2.8","label":"","reference":"Psaumes 2:8","prev_osis_id":"Ps.002.007,fra-LSG","next_osis_id":"Ps.002.009,fra-LSG","text":"<p class=\"q\"><sup id=\"Ps.2.8\" class=\"v\">8<\/sup>Demande-moi et je te donnerai les nations pour h\u00e9ritage,<\/p>\n<p class=\"q\">Les extr\u00e9mit\u00e9s de la terre pour possession;<\/p>","parent":{"chapter":{"path":"\/chapters\/fra-LSG:Ps.2","name":"Psaumes 2","id":"fra-LSG:Ps.2"}},"next":{"verse":{"path":"\/verses\/fra-LSG:Ps.2.9","name":"Psaumes 2:9","id":"fra-LSG:Ps.2.9"}},"previous":{"verse":{"path":"\/verses\/fra-LSG:Ps.2.7","name":"Psaumes 2:7","id":"fra-LSG:Ps.2.7"}},"copyright":"Public Domain"},{"auditid":"0","verse":"9","lastverse":"9","id":"fra-LSG:Ps.2.9","osis_end":"fra-LSG:Ps.2.9","label":"","reference":"Psaumes 2:9","prev_osis_id":"Ps.002.008,fra-LSG","next_osis_id":"Ps.002.010,fra-LSG","text":"<p class=\"q\"><sup id=\"Ps.2.9\" class=\"v\">9<\/sup>\n    Tu les briseras avec une verge de fer,<\/p>\n<p class=\"q\">Tu les briseras comme le vase d\u2019un potier.<\/p>","parent":{"chapter":{"path":"\/chapters\/fra-LSG:Ps.2","name":"Psaumes 2","id":"fra-LSG:Ps.2"}},"next":{"verse":{"path":"\/verses\/fra-LSG:Ps.2.10","name":"Psaumes 2:10","id":"fra-LSG:Ps.2.10"}},"previous":{"verse":{"path":"\/verses\/fra-LSG:Ps.2.8","name":"Psaumes 2:8","id":"fra-LSG:Ps.2.8"}},"copyright":"Public Domain"},{"auditid":"0","verse":"10","lastverse":"10","id":"fra-LSG:Ps.2.10","osis_end":"fra-LSG:Ps.2.10","label":"","reference":"Psaumes 2:10","prev_osis_id":"Ps.002.009,fra-LSG","next_osis_id":"Ps.002.011,fra-LSG","text":"<p class=\"q\"><sup id=\"Ps.2.10\" class=\"v\">10<\/sup>Et maintenant, rois, conduisez-vous avec sagesse!<\/p>\n<p class=\"q\">Juges de la terre, recevez instruction!<\/p>","parent":{"chapter":{"path":"\/chapters\/fra-LSG:Ps.2","name":"Psaumes 2","id":"fra-LSG:Ps.2"}},"next":{"verse":{"path":"\/verses\/fra-LSG:Ps.2.11","name":"Psaumes 2:11","id":"fra-LSG:Ps.2.11"}},"previous":{"verse":{"path":"\/verses\/fra-LSG:Ps.2.9","name":"Psaumes 2:9","id":"fra-LSG:Ps.2.9"}},"copyright":"Public Domain"},{"auditid":"0","verse":"11","lastverse":"11","id":"fra-LSG:Ps.2.11","osis_end":"fra-LSG:Ps.2.11","label":"","reference":"Psaumes 2:11","prev_osis_id":"Ps.002.010,fra-LSG","next_osis_id":"Ps.002.012,fra-LSG","text":"<p class=\"q\"><sup id=\"Ps.2.11\" class=\"v\">11<\/sup>Servez l\u2019\u00c9ternel avec crainte,<\/p>\n<p class=\"q\">Et r\u00e9jouissez-vous avec tremblement.<\/p>","parent":{"chapter":{"path":"\/chapters\/fra-LSG:Ps.2","name":"Psaumes 2","id":"fra-LSG:Ps.2"}},"next":{"verse":{"path":"\/verses\/fra-LSG:Ps.2.12","name":"Psaumes 2:12","id":"fra-LSG:Ps.2.12"}},"previous":{"verse":{"path":"\/verses\/fra-LSG:Ps.2.10","name":"Psaumes 2:10","id":"fra-LSG:Ps.2.10"}},"copyright":"Public Domain"},{"auditid":"0","verse":"12","lastverse":"12","id":"fra-LSG:Ps.2.12","osis_end":"fra-LSG:Ps.2.12","label":"","reference":"Psaumes 2:12","prev_osis_id":"Ps.002.011,fra-LSG","next_osis_id":"Ps.003.001,fra-LSG","text":"<p class=\"q\"><sup id=\"Ps.2.12\" class=\"v\">12<\/sup>Baisez le fils, de peur qu\u2019il ne s\u2019irrite,<\/p>\n<p class=\"q\">Et que vous ne p\u00e9rissiez dans votre voie,<\/p>\n<p class=\"q\">Car sa col\u00e8re est prompte \u00e0 s\u2019enflammer.<\/p>\n<p class=\"q\">\n    Heureux tous ceux qui se confient en lui!<\/p>","parent":{"chapter":{"path":"\/chapters\/fra-LSG:Ps.2","name":"Psaumes 2","id":"fra-LSG:Ps.2"}},"next":{"verse":{"path":"\/verses\/fra-LSG:Ps.3.1","name":"Psaumes 3:1","id":"fra-LSG:Ps.3.1"}},"previous":{"verse":{"path":"\/verses\/fra-LSG:Ps.2.11","name":"Psaumes 2:11","id":"fra-LSG:Ps.2.11"}},"copyright":"Public Domain"}],"meta":{"fums":"<script>\nvar _BAPI=_BAPI||{};\nif(typeof(_BAPI.t)==='undefined'){\ndocument.write('\\x3Cscript src=\"'+document.location.protocol+'\/\/d2ue49q0mum86x.cloudfront.net\/include\/fums.c.js\"\\x3E\\x3C\/script\\x3E');}\ndocument.write(\"\\x3Cscript\\x3E_BAPI.t('5af81fbabd87e2.65695575');\\x3C\/script\\x3E\");\n<\/script><noscript><img src=\"https:\/\/d3a2okcloueqyx.cloudfront.net\/nf1?t=5af81fbabd87e2.65695575\" height=\"1\" width=\"1\" border=\"0\" alt=\"\" style=\"height: 0; width: 0;\" \/><\/noscript>","fums_tid":"5af81fbabd87e2.65695575","fums_js_include":"d2ue49q0mum86x.cloudfront.net\/include\/fums.c.js","fums_js":"var _BAPI=_BAPI||{};if(typeof(_BAPI.t)!='undefined'){ _BAPI.t('5af81fbabd87e2.65695575'); }","fums_noscript":"<img src=\"https:\/\/d3a2okcloueqyx.cloudfront.net\/nf1?t=5af81fbabd87e2.65695575\" height=\"1\" width=\"1\" border=\"0\" alt=\"\" style=\"height: 0; width: 0;\" \/>"}}}