{"response":{"verses":[{"auditid":"0","verse":"1","lastverse":"1","id":"fra-LSG:Hos.11.1","osis_end":"fra-LSG:Hos.11.1","label":"","reference":"Os\u00e9e 11:1","prev_osis_id":"Hos.010.015,fra-LSG","next_osis_id":"Hos.011.002,fra-LSG","text":"<h3 class=\"s\">Ingratitude d\u2019Isra\u00ebl et compassion de Dieu<\/h3>\n<h5 class=\"r\">V. 1-7: cf. J\u00e9 2:1-9. De 32:9-25.<\/h5>\n<p class=\"q\"><sup id=\"Hos.11.1\" class=\"v\">1<\/sup>Quand Isra\u00ebl \u00e9tait jeune, je l\u2019aimais,<\/p>\n<p class=\"q\">\n    Et j\u2019appelai mon fils hors d\u2019\u00c9gypte.<\/p>","parent":{"chapter":{"path":"\/chapters\/fra-LSG:Hos.11","name":"Os\u00e9e 11","id":"fra-LSG:Hos.11"}},"next":{"verse":{"path":"\/verses\/fra-LSG:Hos.11.2","name":"Os\u00e9e 11:2","id":"fra-LSG:Hos.11.2"}},"previous":{"verse":{"path":"\/verses\/fra-LSG:Hos.10.15","name":"Os\u00e9e 10:15","id":"fra-LSG:Hos.10.15"}},"copyright":"Public Domain"},{"auditid":"0","verse":"2","lastverse":"2","id":"fra-LSG:Hos.11.2","osis_end":"fra-LSG:Hos.11.2","label":"","reference":"Os\u00e9e 11:2","prev_osis_id":"Hos.011.001,fra-LSG","next_osis_id":"Hos.011.003,fra-LSG","text":"<p class=\"q\"><sup id=\"Hos.11.2\" class=\"v\">2<\/sup>Mais ils se sont \u00e9loign\u00e9s de ceux qui les appelaient;<\/p>\n<p class=\"q\">Ils ont sacrifi\u00e9 aux Baals,<\/p>\n<p class=\"q\">Et offert de l\u2019encens aux idoles.<\/p>","parent":{"chapter":{"path":"\/chapters\/fra-LSG:Hos.11","name":"Os\u00e9e 11","id":"fra-LSG:Hos.11"}},"next":{"verse":{"path":"\/verses\/fra-LSG:Hos.11.3","name":"Os\u00e9e 11:3","id":"fra-LSG:Hos.11.3"}},"previous":{"verse":{"path":"\/verses\/fra-LSG:Hos.11.1","name":"Os\u00e9e 11:1","id":"fra-LSG:Hos.11.1"}},"copyright":"Public Domain"},{"auditid":"0","verse":"3","lastverse":"3","id":"fra-LSG:Hos.11.3","osis_end":"fra-LSG:Hos.11.3","label":"","reference":"Os\u00e9e 11:3","prev_osis_id":"Hos.011.002,fra-LSG","next_osis_id":"Hos.011.004,fra-LSG","text":"<p class=\"q\"><sup id=\"Hos.11.3\" class=\"v\">3<\/sup>C\u2019est moi qui guidai les pas d\u2019\u00c9phra\u00efm,<\/p>\n<p class=\"q\">Le soutenant par ses bras;<\/p>\n<p class=\"q\">Et ils n\u2019ont pas vu que je les gu\u00e9rissais.<\/p>","parent":{"chapter":{"path":"\/chapters\/fra-LSG:Hos.11","name":"Os\u00e9e 11","id":"fra-LSG:Hos.11"}},"next":{"verse":{"path":"\/verses\/fra-LSG:Hos.11.4","name":"Os\u00e9e 11:4","id":"fra-LSG:Hos.11.4"}},"previous":{"verse":{"path":"\/verses\/fra-LSG:Hos.11.2","name":"Os\u00e9e 11:2","id":"fra-LSG:Hos.11.2"}},"copyright":"Public Domain"},{"auditid":"0","verse":"4","lastverse":"4","id":"fra-LSG:Hos.11.4","osis_end":"fra-LSG:Hos.11.4","label":"","reference":"Os\u00e9e 11:4","prev_osis_id":"Hos.011.003,fra-LSG","next_osis_id":"Hos.011.005,fra-LSG","text":"<p class=\"q\"><sup id=\"Hos.11.4\" class=\"v\">4<\/sup>Je les tirai avec des liens d\u2019humanit\u00e9, avec des cordages d\u2019amour,<\/p>\n<p class=\"q\">Je fus pour eux comme celui qui aurait rel\u00e2ch\u00e9 le joug pr\u00e8s de leur bouche,<\/p>\n<p class=\"q\">Et je leur pr\u00e9sentai de la nourriture.<\/p>","parent":{"chapter":{"path":"\/chapters\/fra-LSG:Hos.11","name":"Os\u00e9e 11","id":"fra-LSG:Hos.11"}},"next":{"verse":{"path":"\/verses\/fra-LSG:Hos.11.5","name":"Os\u00e9e 11:5","id":"fra-LSG:Hos.11.5"}},"previous":{"verse":{"path":"\/verses\/fra-LSG:Hos.11.3","name":"Os\u00e9e 11:3","id":"fra-LSG:Hos.11.3"}},"copyright":"Public Domain"},{"auditid":"0","verse":"5","lastverse":"5","id":"fra-LSG:Hos.11.5","osis_end":"fra-LSG:Hos.11.5","label":"","reference":"Os\u00e9e 11:5","prev_osis_id":"Hos.011.004,fra-LSG","next_osis_id":"Hos.011.006,fra-LSG","text":"<p class=\"q\"><sup id=\"Hos.11.5\" class=\"v\">5<\/sup>Ils ne retourneront pas au pays d\u2019\u00c9gypte;<\/p>\n<p class=\"q\">Mais l\u2019Assyrien sera leur roi,<\/p>\n<p class=\"q\">Parce qu\u2019ils ont refus\u00e9 de revenir \u00e0 moi.<\/p>","parent":{"chapter":{"path":"\/chapters\/fra-LSG:Hos.11","name":"Os\u00e9e 11","id":"fra-LSG:Hos.11"}},"next":{"verse":{"path":"\/verses\/fra-LSG:Hos.11.6","name":"Os\u00e9e 11:6","id":"fra-LSG:Hos.11.6"}},"previous":{"verse":{"path":"\/verses\/fra-LSG:Hos.11.4","name":"Os\u00e9e 11:4","id":"fra-LSG:Hos.11.4"}},"copyright":"Public Domain"},{"auditid":"0","verse":"6","lastverse":"6","id":"fra-LSG:Hos.11.6","osis_end":"fra-LSG:Hos.11.6","label":"","reference":"Os\u00e9e 11:6","prev_osis_id":"Hos.011.005,fra-LSG","next_osis_id":"Hos.011.007,fra-LSG","text":"<p class=\"q\"><sup id=\"Hos.11.6\" class=\"v\">6<\/sup>L\u2019\u00e9p\u00e9e fondra sur leurs villes,<\/p>\n<p class=\"q\">An\u00e9antira, d\u00e9vorera leurs soutiens,<\/p>\n<p class=\"q\">A cause des desseins qu\u2019ils ont eus.<\/p>","parent":{"chapter":{"path":"\/chapters\/fra-LSG:Hos.11","name":"Os\u00e9e 11","id":"fra-LSG:Hos.11"}},"next":{"verse":{"path":"\/verses\/fra-LSG:Hos.11.7","name":"Os\u00e9e 11:7","id":"fra-LSG:Hos.11.7"}},"previous":{"verse":{"path":"\/verses\/fra-LSG:Hos.11.5","name":"Os\u00e9e 11:5","id":"fra-LSG:Hos.11.5"}},"copyright":"Public Domain"},{"auditid":"0","verse":"7","lastverse":"7","id":"fra-LSG:Hos.11.7","osis_end":"fra-LSG:Hos.11.7","label":"","reference":"Os\u00e9e 11:7","prev_osis_id":"Hos.011.006,fra-LSG","next_osis_id":"Hos.011.008,fra-LSG","text":"<p class=\"q\"><sup id=\"Hos.11.7\" class=\"v\">7<\/sup>Mon peuple est enclin \u00e0 s\u2019\u00e9loigner de moi;<\/p>\n<p class=\"q\">On les rappelle vers le Tr\u00e8s-Haut,<\/p>\n<p class=\"q\">Mais aucun d\u2019eux ne l\u2019exalte.<\/p>","parent":{"chapter":{"path":"\/chapters\/fra-LSG:Hos.11","name":"Os\u00e9e 11","id":"fra-LSG:Hos.11"}},"next":{"verse":{"path":"\/verses\/fra-LSG:Hos.11.8","name":"Os\u00e9e 11:8","id":"fra-LSG:Hos.11.8"}},"previous":{"verse":{"path":"\/verses\/fra-LSG:Hos.11.6","name":"Os\u00e9e 11:6","id":"fra-LSG:Hos.11.6"}},"copyright":"Public Domain"},{"auditid":"0","verse":"8","lastverse":"8","id":"fra-LSG:Hos.11.8","osis_end":"fra-LSG:Hos.11.8","label":"","reference":"Os\u00e9e 11:8","prev_osis_id":"Hos.011.007,fra-LSG","next_osis_id":"Hos.011.009,fra-LSG","text":"<h5 class=\"r\">V. 8-11: cf. J\u00e9 31:18-21. \u00c9s 27:12, 13.<\/h5>\n<p class=\"q\"><sup id=\"Hos.11.8\" class=\"v\">8<\/sup>Que ferai-je de toi, \u00c9phra\u00efm?<\/p>\n<p class=\"q\">Dois-je te livrer, Isra\u00ebl?<\/p>\n<p class=\"q\">Te traiterai-je comme Adma?<\/p>\n<p class=\"q\">Te rendrai-je semblable \u00e0 Tsebo\u00efm?<\/p>\n<p class=\"q\">Mon c\u0153ur s\u2019agite au-dedans de moi,<\/p>\n<p class=\"q\">Toutes mes compassions sont \u00e9mues.<\/p>","parent":{"chapter":{"path":"\/chapters\/fra-LSG:Hos.11","name":"Os\u00e9e 11","id":"fra-LSG:Hos.11"}},"next":{"verse":{"path":"\/verses\/fra-LSG:Hos.11.9","name":"Os\u00e9e 11:9","id":"fra-LSG:Hos.11.9"}},"previous":{"verse":{"path":"\/verses\/fra-LSG:Hos.11.7","name":"Os\u00e9e 11:7","id":"fra-LSG:Hos.11.7"}},"copyright":"Public Domain"},{"auditid":"0","verse":"9","lastverse":"9","id":"fra-LSG:Hos.11.9","osis_end":"fra-LSG:Hos.11.9","label":"","reference":"Os\u00e9e 11:9","prev_osis_id":"Hos.011.008,fra-LSG","next_osis_id":"Hos.011.010,fra-LSG","text":"<p class=\"q\"><sup id=\"Hos.11.9\" class=\"v\">9<\/sup>Je n\u2019agirai pas selon mon ardente col\u00e8re,<\/p>\n<p class=\"q\">Je renonce \u00e0 d\u00e9truire \u00c9phra\u00efm;<\/p>\n<p class=\"q\">Car je suis Dieu, et non pas un homme,<\/p>\n<p class=\"q\">Je suis le Saint au milieu de toi;<\/p>\n<p class=\"q\">Je ne viendrai pas avec col\u00e8re.<\/p>","parent":{"chapter":{"path":"\/chapters\/fra-LSG:Hos.11","name":"Os\u00e9e 11","id":"fra-LSG:Hos.11"}},"next":{"verse":{"path":"\/verses\/fra-LSG:Hos.11.10","name":"Os\u00e9e 11:10","id":"fra-LSG:Hos.11.10"}},"previous":{"verse":{"path":"\/verses\/fra-LSG:Hos.11.8","name":"Os\u00e9e 11:8","id":"fra-LSG:Hos.11.8"}},"copyright":"Public Domain"},{"auditid":"0","verse":"10","lastverse":"10","id":"fra-LSG:Hos.11.10","osis_end":"fra-LSG:Hos.11.10","label":"","reference":"Os\u00e9e 11:10","prev_osis_id":"Hos.011.009,fra-LSG","next_osis_id":"Hos.011.011,fra-LSG","text":"<p class=\"q\"><sup id=\"Hos.11.10\" class=\"v\">10<\/sup>Ils suivront l\u2019\u00c9ternel, qui rugira comme un lion,<\/p>\n<p class=\"q\">Car il rugira, et les enfants accourront de la mer.<\/p>","parent":{"chapter":{"path":"\/chapters\/fra-LSG:Hos.11","name":"Os\u00e9e 11","id":"fra-LSG:Hos.11"}},"next":{"verse":{"path":"\/verses\/fra-LSG:Hos.11.11","name":"Os\u00e9e 11:11","id":"fra-LSG:Hos.11.11"}},"previous":{"verse":{"path":"\/verses\/fra-LSG:Hos.11.9","name":"Os\u00e9e 11:9","id":"fra-LSG:Hos.11.9"}},"copyright":"Public Domain"},{"auditid":"0","verse":"11","lastverse":"11","id":"fra-LSG:Hos.11.11","osis_end":"fra-LSG:Hos.11.11","label":"","reference":"Os\u00e9e 11:11","prev_osis_id":"Hos.011.010,fra-LSG","next_osis_id":"Hos.012.001,fra-LSG","text":"<p class=\"q\"><sup id=\"Hos.11.11\" class=\"v\">11<\/sup>Ils accourront de l\u2019\u00c9gypte, comme un oiseau,<\/p>\n<p class=\"q\">Et du pays d\u2019Assyrie, comme une colombe.<\/p>\n<p class=\"q\">Et je les ferai habiter dans leurs maisons, dit l\u2019\u00c9ternel.<\/p>","parent":{"chapter":{"path":"\/chapters\/fra-LSG:Hos.11","name":"Os\u00e9e 11","id":"fra-LSG:Hos.11"}},"next":{"verse":{"path":"\/verses\/fra-LSG:Hos.12.1","name":"Os\u00e9e 12:1","id":"fra-LSG:Hos.12.1"}},"previous":{"verse":{"path":"\/verses\/fra-LSG:Hos.11.10","name":"Os\u00e9e 11:10","id":"fra-LSG:Hos.11.10"}},"copyright":"Public Domain"}],"meta":{"fums":"<script>\nvar _BAPI=_BAPI||{};\nif(typeof(_BAPI.t)==='undefined'){\ndocument.write('\\x3Cscript src=\"'+document.location.protocol+'\/\/d2ue49q0mum86x.cloudfront.net\/include\/fums.c.js\"\\x3E\\x3C\/script\\x3E');}\ndocument.write(\"\\x3Cscript\\x3E_BAPI.t('5af81fbb0ff100.47407384');\\x3C\/script\\x3E\");\n<\/script><noscript><img src=\"https:\/\/d3a2okcloueqyx.cloudfront.net\/nf1?t=5af81fbb0ff100.47407384\" height=\"1\" width=\"1\" border=\"0\" alt=\"\" style=\"height: 0; width: 0;\" \/><\/noscript>","fums_tid":"5af81fbb0ff100.47407384","fums_js_include":"d2ue49q0mum86x.cloudfront.net\/include\/fums.c.js","fums_js":"var _BAPI=_BAPI||{};if(typeof(_BAPI.t)!='undefined'){ _BAPI.t('5af81fbb0ff100.47407384'); }","fums_noscript":"<img src=\"https:\/\/d3a2okcloueqyx.cloudfront.net\/nf1?t=5af81fbb0ff100.47407384\" height=\"1\" width=\"1\" border=\"0\" alt=\"\" style=\"height: 0; width: 0;\" \/>"}}}